mkdocs_landing/__init__.py
mkdocs_landing/article.html
mkdocs_landing/filters.py
mkdocs_landing/links.html
mkdocs_landing/main.html
mkdocs_landing/mkdocs_theme.yml
mkdocs_landing/assets/landing-background.png
mkdocs_landing/assets/landing-favicon.png
mkdocs_landing/assets/landing-logo.png
mkdocs_landing/assets/fonts/emoji/NotoColorEmoji-Regular.ttf
mkdocs_landing/css/links.css
mkdocs_landing/css/responsivity.css
mkdocs_landing/css/style.css
mkdocs_landing/partials/article_header.html
mkdocs_landing/partials/footer.html
mkdocs_landing/partials/head_config.html
mkdocs_landing/partials/header_element.html
mkdocs_landing/partials/homepage_header.html
mkdocs_landing/partials/share_btn.html
mkdocs_landing/partials/toc.html
mkdocs_landing-0.0.8.dist-info/METADATA
mkdocs_landing-0.0.8.dist-info/WHEEL
mkdocs_landing-0.0.8.dist-info/entry_points.txt
mkdocs_landing-0.0.8.dist-info/top_level.txt
mkdocs_landing-0.0.8.dist-info/RECORD
