Metadata-Version: 2.1
Name: mkdocs-landing
Version: 0.0.8
Summary: mkdocs theme geared towards making a personal landing page, with simpler navigation and heavily customisable style options.
Author-email: Todd Parsons <todd.e.parsons@gmail.com>
Project-URL: Homepage, https://TEParsons.github.io/mkdocs-landing
Project-URL: Download, https://github.com/TEParsons/mkdocs-landing/releases
Requires-Dist: mkdocs
Provides-Extra: tests
Requires-Dist: pytest; extra == "tests"
Requires-Dist: httpx; extra == "tests"
Requires-Dist: pyyaml; extra == "tests"
Requires-Dist: mkdocs-get-deps; extra == "tests"
Requires-Dist: mkdocs-material; extra == "tests"
Requires-Dist: shot-scraper; extra == "tests"
Requires-Dist: jinja2; extra == "tests"
Requires-Dist: tqdm; extra == "tests"
Requires-Dist: uv; extra == "tests"
Requires-Dist: mkdocstrings-python; extra == "tests"
